pyhank/__init__.py
pyhank/hankel.py
pyhank/one_shot.py
pyhank-2.4.0.dist-info/LICENSE.txt
pyhank-2.4.0.dist-info/METADATA
pyhank-2.4.0.dist-info/WHEEL
pyhank-2.4.0.dist-info/top_level.txt
pyhank-2.4.0.dist-info/RECORD
