Metadata-Version: 2.1
Name: pyhank
Version: 2.4.0
Summary: pyhank - Quasi-discrete Hankel transforms for python
Home-page: https://github.com/etfrogers/pyhank
Author: Edward Rogers
Author-email: etfrogers@hotmail.com
License: UNKNOWN
Platform: UNKNOWN
Classifier: Programming Language :: Python :: 3
Classifier: License :: OSI Approved :: MIT License
Classifier: Operating System :: OS Independent
Requires-Python: ~=3.6
License-File: LICENSE.txt
Requires-Dist: numpy (~=1.15)
Requires-Dist: scipy (~=1.0)
